[{"platform": "chrome", "id": "nobcanbppjbdddoilcpahbkdmjjihnem", "key": "bittrend", "name": "BitTrend", "rating": 0.0, "user_numbers": "12", "creator": "Media3", "last_updated": "2014-09-04 00:00:00"}, {"platform": "chrome", "id": "giehkbmaeanabblbpagkonkbjdjhnlgl", "key": "citify-instant-exchange", "name": "Citify Instant Exchange", "rating": 0.0, "user_numbers": "10", "creator": "Citify", "last_updated": "2019-09-10 00:00:00"}, {"platform": "chrome", "id": "caknhbobbhcehjebdcpgfodgfbpklblm", "key": "cryptonow", "name": "CryptoNow", "rating": 5.0, "user_numbers": "7", "creator": "jessica.greben1", "last_updated": "2017-05-15 00:00:00"}, {"platform": "chrome", "id": "eeejeggpdpjgkfocdkbepdbkpcpjlncd", "key": "bit-trackers", "name": "Bit Trackers", "rating": 5.0, "user_numbers": "5", "creator": "satyamdev123", "last_updated": "2017-07-13 00:00:00"}, {"platform": "chrome", "id": "pnndplcbkakcplkjnolgbkdgjikjednm", "key": "tron-wallet-explorer-tron", "name": "Tron Wallet & Explorer - Tronium", "rating": 4.1, "user_numbers": "2,000", "creator": "syattdevelopment", "last_updated": "2020-10-19 00:00:00"}, {"platform": "chrome", "id": "djhecjelehcfnnlbkegkckcngmngdnjf", "key": "reynapay", "name": "ReynaPay", "rating": 3.6666666666666665, "user_numbers": "11", "creator": "Reyna Foundation", "last_updated": "2020-01-15 00:00:00"}, {"platform": "chrome", "id": "bkdlmhjcfkfainkpdcdnaefganapmblg", "key": "skywallet", "name": "SkyWallet", "rating": 0.0, "user_numbers": "5", "creator": "developer", "last_updated": "2020-06-13 00:00:00"}, {"platform": "chrome", "id": "nobcanbppjbdddoilcpahbkdmjjihnem", "key": "bittrend", "name": "BitTrend", "rating": 0.0, "user_numbers": "12", "creator": "Media3", "last_updated": "2014-09-04 00:00:00"}, {"platform": "chrome", "id": "giehkbmaeanabblbpagkonkbjdjhnlgl", "key": "citify-instant-exchange", "name": "Citify Instant Exchange", "rating": 0.0, "user_numbers": "10", "creator": "Citify", "last_updated": "2019-09-10 00:00:00"}, {"platform": "chrome", "id": "caknhbobbhcehjebdcpgfodgfbpklblm", "key": "cryptonow", "name": "CryptoNow", "rating": 5.0, "user_numbers": "7", "creator": "jessica.greben1", "last_updated": "2017-05-15 00:00:00"}, {"platform": "chrome", "id": "eeejeggpdpjgkfocdkbepdbkpcpjlncd", "key": "bit-trackers", "name": "Bit Trackers", "rating": 5.0, "user_numbers": "5", "creator": "satyamdev123", "last_updated": "2017-07-13 00:00:00"}, {"platform": "chrome", "id": "pnndplcbkakcplkjnolgbkdgjikjednm", "key": "tron-wallet-explorer-tron", "name": "Tron Wallet & Explorer - Tronium", "rating": 4.1, "user_numbers": "2,000", "creator": "syattdevelopment", "last_updated": "2020-10-19 00:00:00"}, {"platform": "chrome", "id": "djhecjelehcfnnlbkegkckcngmngdnjf", "key": "reynapay", "name": "ReynaPay", "rating": 3.6666666666666665, "user_numbers": "11", "creator": "Reyna Foundation", "last_updated": "2020-01-15 00:00:00"}, {"platform": "chrome", "id": "bkdlmhjcfkfainkpdcdnaefganapmblg", "key": "skywallet", "name": "SkyWallet", "rating": 0.0, "user_numbers": "5", "creator": "developer", "last_updated": "2020-06-13 00:00:00"}, {"platform": "chrome", "id": "laphpbhjhhgigmjoflgcchgodbbclahk", "key": "blue-worlds-safest-simple", "name": "BLUE - World's Safest & Simplest Wallet", "rating": 5.0, "user_numbers": "1,000", "creator": "etherbluewallet", "last_updated": "2019-09-17 00:00:00"}, {"platform": "chrome", "id": "kpfopkelmapcoipemfendmdcghnegimn", "key": "liquality-wallet", "name": "Liquality Wallet", "rating": 5.0, "user_numbers": "882", "creator": "Liquality", "last_updated": "2020-12-07 00:00:00"}, {"platform": "chrome", "id": "injlalemmnakihphncnhbdckncjbcaac", "key": "waifuchain", "name": "WaifuChain", "rating": 0.0, "user_numbers": "72", "creator": "corollari", "last_updated": "2019-03-23 00:00:00"}, {"platform": "chrome", "id": "dmbgoabeajhaepagmjnilmpmfhjljdba", "key": "ethereum-pre\u00e7o-hoje", "name": "Ethereum Pre\u00e7o Hoje", "rating": 0.0, "user_numbers": "1", "creator": "landuartoficial", "last_updated": "2019-10-29 00:00:00"}, {"platform": "chrome", "id": "nogdkjfnegdjdgegekcclglocakclegl", "key": "bitcoin-ticker-for-wex-ex", "name": "Bitcoin Ticker for WEX exchange", "rating": 4.833333333333333, "user_numbers": "19", "creator": "Maksym Tymchyk", "last_updated": "2020-08-27 00:00:00"}, {"platform": "chrome", "id": "efmkodhojilpinbapdnoeikgabdclhfg", "key": "cointrack", "name": "Cointrack", "rating": 5.0, "user_numbers": "16", "creator": "Abiodun Adetona", "last_updated": "2017-11-04 00:00:00"}, {"platform": "chrome", "id": "omlcemhghhleeoaoodlipigplhccodbp", "key": "cryptocurrency-price-moni", "name": "Cryptocurrency Price monitoring", "rating": 5.0, "user_numbers": "13", "creator": "Rakesh Narvaneni", "last_updated": "2017-12-31 00:00:00"}, {"platform": "chrome", "id": "giehkbmaeanabblbpagkonkbjdjhnlgl", "key": "citify-instant-exchange", "name": "Citify Instant Exchange", "rating": 0.0, "user_numbers": "11", "creator": "Citify", "last_updated": "2019-09-10 00:00:00"}, {"platform": "chrome", "id": "nobcanbppjbdddoilcpahbkdmjjihnem", "key": "bittrend", "name": "BitTrend", "rating": 0.0, "user_numbers": "11", "creator": "Media3", "last_updated": "2014-09-04 00:00:00"}, {"platform": "chrome", "id": "caknhbobbhcehjebdcpgfodgfbpklblm", "key": "cryptonow", "name": "CryptoNow", "rating": 5.0, "user_numbers": "7", "creator": "jessica.greben1", "last_updated": "2017-05-15 00:00:00"}, {"platform": "chrome", "id": "eeejeggpdpjgkfocdkbepdbkpcpjlncd", "key": "bit-trackers", "name": "Bit Trackers", "rating": 5.0, "user_numbers": "6", "creator": "satyamdev123", "last_updated": "2017-07-13 00:00:00"}, {"platform": "chrome", "id": "glaoldjgoiaajcjcbgpfmnfddioaolop", "key": "cryptocoins-live-rates", "name": "CryptoCoins - Live Rates", "rating": 5.0, "user_numbers": "2", "creator": "ganeshpartheeban", "last_updated": "2019-02-13 00:00:00"}, {"platform": "chrome", "id": "jedgfcnbkbgiheojcfkbphplgkhgppgf", "key": "ethereum-allinone-eth-tic", "name": "Ethereum AllInOne: ETH Ticker / Wallet viewer", "rating": 4.5, "user_numbers": "39", "creator": "Zed's Dev", "last_updated": "2017-12-06 00:00:00"}, {"platform": "chrome", "id": "nbdanhiimhghdlhjnjeplpplojecnjmh", "key": "eth-price-ethereum", "name": "ETH price (Ethereum)", "rating": 3.875, "user_numbers": "854", "creator": "Ra\u00fal Marcos", "last_updated": "2017-08-28 00:00:00"}, {"platform": "chrome", "id": "lbggcmmelaomcbgmeccjfejpamehbhin", "key": "yezcoin-ethereum-scam-add", "name": "Yezcoin Ethereum Scam Address Detector", "rating": 5.0, "user_numbers": "21", "creator": "Yezcoin Pte.Ltd.", "last_updated": "2018-07-16 00:00:00"}, {"platform": "chrome", "id": "dlnalaneihafdkdcekejdekiclgdghka", "key": "breadcrumbs-blockchain-in", "name": "Breadcrumbs Blockchain Investigate", "rating": 5.0, "user_numbers": "26", "creator": "Breadcrumbs", "last_updated": "2020-08-22 00:00:00"}, {"platform": "chrome", "id": "mblpipfoicjgcokcnnmbebnlooldfdjc", "key": "ethereum-tracker-euro-pri", "name": "Ethereum Tracker - Euro Price (ETHEUR)", "rating": 5.0, "user_numbers": "16", "creator": "HamsterApps", "last_updated": "2017-05-04 00:00:00"}, {"platform": "chrome", "id": "dconegbmnkoeccohdkifggkgdhoaedgc", "key": "ethereum-ethusd-price-tic", "name": "Ethereum (ETH/USD) Price Ticker", "rating": 5.0, "user_numbers": "73", "creator": "Taha", "last_updated": "2020-03-20 00:00:00"}, {"platform": "chrome", "id": "eifglbbbdbmfcjoeeokmpdmhkhcilfil", "key": "ethereum", "name": "Ethereum", "rating": 5.0, "user_numbers": "11", "creator": "lexansoft", "last_updated": "2016-02-18 00:00:00"}, {"platform": "chrome", "id": "egjiglhnofaenmabafhplabgimbcmlgf", "key": "ethereum-toolkit", "name": "Ethereum toolkit", "rating": 5.0, "user_numbers": "8", "creator": "hylsceptic", "last_updated": "2018-08-13 00:00:00"}, {"platform": "chrome", "id": "eachlnokbkckmbhglohpcmhllebcdbme", "key": "ethereum-price-ticker-ale", "name": "Ethereum Price Ticker & Alert", "rating": 0.0, "user_numbers": "5", "creator": "happy elephant web development", "last_updated": "2020-09-08 00:00:00"}, {"platform": "chrome", "id": "caddnmdigajdehmjbnlkpmnckkcneckf", "key": "ethereum-price-in-usd-by", "name": "Ethereum price in USD by BitcoinFan", "rating": 5.0, "user_numbers": "5", "creator": "BitcoinFan", "last_updated": "2020-12-12 00:00:00"}, {"platform": "chrome", "id": "gmmnjkphjfnanlojihefoeidjmbakfde", "key": "ethereum-price-in-eur-by", "name": "Ethereum price in EUR by BitcoinFan", "rating": 5.0, "user_numbers": "3", "creator": "BitcoinFan", "last_updated": "2020-12-12 00:00:00"}, {"platform": "chrome", "id": "fekkpefadofgnlkageinocamiapffnak", "key": "cryptokitties-finder", "name": "CryptoKitties Finder", "rating": 0.0, "user_numbers": "61", "creator": "Francesco Megna", "last_updated": "2018-04-05 00:00:00"}, {"platform": "chrome", "id": "ainmgbleakflfgjjoolgmgfepddnpeln", "key": "ethereum-monitor", "name": "Ethereum monitor", "rating": 0.0, "user_numbers": "2", "creator": "Awork", "last_updated": "2020-07-15 00:00:00"}, {"platform": "chrome", "id": "bbmdccojdbpcpmoadenplnoncfcijgkn", "key": "onewallet-kratos-mainnet", "name": "OneWallet Kratos Mainnet", "rating": 5.0, "user_numbers": "302", "creator": "OneLedger Technologies Inc.", "last_updated": "2020-09-01 00:00:00"}, {"platform": "chrome", "id": "gdocmelgnjeejhlphdnoocikeafdpaep", "key": "gitcoin", "name": "Gitcoin", "rating": 5.0, "user_numbers": "207", "creator": "ksowocki", "last_updated": "2019-04-29 00:00:00"}, {"platform": "chrome", "id": "achbehnmipmphllfekbgjjdmhehbgoce", "key": "ether-sneak-peek", "name": "Ether Sneak Peek", "rating": 3.0, "user_numbers": "66", "creator": "steven2358", "last_updated": "2017-07-25 00:00:00"}, {"platform": "chrome", "id": "dmbgoabeajhaepagmjnilmpmfhjljdba", "key": "ethereum-pre\u00e7o-hoje", "name": "Ethereum Pre\u00e7o Hoje", "rating": 0.0, "user_numbers": "2", "creator": "landuartoficial", "last_updated": "2019-10-29 00:00:00"}, {"platform": "chrome", "id": "fceaohfigonmbbdecpbjjhkafciaiomf", "key": "bitcoin-ticker", "name": "BitCoin Ticker", "rating": 4.0, "user_numbers": "10", "creator": "dana11235", "last_updated": "2017-09-25 00:00:00"}, {"platform": "chrome", "id": "akfogaiaahkdhpgihkcdncbhmkjjfban", "key": "crypto-ticker", "name": "Crypto Ticker", "rating": 1.0, "user_numbers": "6", "creator": "CodeTheBay", "last_updated": "2019-01-02 00:00:00"}, {"platform": "chrome", "id": "fdahclgkkbnjkfcngfbohobpmedlcfpm", "key": "algorand-wallet", "name": "Algorand Wallet", "rating": 0.0, "user_numbers": "48", "creator": "Pibals", "last_updated": "2020-01-25 00:00:00"}, {"platform": "chrome", "id": "achbehnmipmphllfekbgjjdmhehbgoce", "key": "ether-sneak-peek", "name": "Ether Sneak Peek", "rating": 3.0, "user_numbers": "66", "creator": "steven2358", "last_updated": "2017-07-25 00:00:00"}, {"platform": "chrome", "id": "dmbgoabeajhaepagmjnilmpmfhjljdba", "key": "ethereum-pre\u00e7o-hoje", "name": "Ethereum Pre\u00e7o Hoje", "rating": 0.0, "user_numbers": "2", "creator": "landuartoficial", "last_updated": "2019-10-29 00:00:00"}, {"platform": "chrome", "id": "fceaohfigonmbbdecpbjjhkafciaiomf", "key": "bitcoin-ticker", "name": "BitCoin Ticker", "rating": 4.0, "user_numbers": "9", "creator": "dana11235", "last_updated": "2017-09-25 00:00:00"}, {"platform": "chrome", "id": "llpbjcejemjfaicajiephoejjnogfbed", "key": "bitcoin-tab", "name": "Bitcoin Tab", "rating": 0.0, "user_numbers": "8", "creator": "Bitcoin Tab", "last_updated": "2020-11-29 00:00:00"}, {"platform": "chrome", "id": "akfogaiaahkdhpgihkcdncbhmkjjfban", "key": "crypto-ticker", "name": "Crypto Ticker", "rating": 1.0, "user_numbers": "6", "creator": "CodeTheBay", "last_updated": "2019-01-02 00:00:00"}, {"platform": "chrome", "id": "lbcjaollbgiecemkpbllpkbeffegcllo", "key": "cryptotabs", "name": "CryptoTabs", "rating": 4.642857142857143, "user_numbers": "1,000", "creator": "Tyler Wolff", "last_updated": "2019-07-16 00:00:00"}, {"platform": "chrome", "id": "cjbbladbihgdplijjgkakilcofhbhnea", "key": "litecoin-pre\u00e7o-hoje", "name": "Litecoin Pre\u00e7o Hoje", "rating": 0.0, "user_numbers": "1", "creator": "landuartoficial", "last_updated": "2018-08-28 00:00:00"}, {"platform": "chrome", "id": "mbaihdegekjkhgajmamfgmgephoeppgb", "key": "just-litecoin-ticker-pro", "name": "Just Litecoin Ticker [PRO]", "rating": 0.0, "user_numbers": "1", "creator": "morocco", "last_updated": "2020-11-03 00:00:00"}, {"platform": "chrome", "id": "oheacmjjkbcbpgmdljkbcaopcmpjfloj", "key": "tps-brainwallet", "name": "TP's Brainwallet", "rating": 5.0, "user_numbers": "125", "creator": "tpidev", "last_updated": "2013-06-01 00:00:00"}, {"platform": "chrome", "id": "mkekmkkaginnjcoicjcoieodjmbbnfcb", "key": "coinvaluegatherer", "name": "CoinValueGatherer", "rating": 4.8, "user_numbers": "100", "creator": "alexvales111", "last_updated": "2017-12-21 00:00:00"}, {"platform": "chrome", "id": "nogdkjfnegdjdgegekcclglocakclegl", "key": "bitcoin-ticker-for-wex-ex", "name": "Bitcoin Ticker for WEX exchange", "rating": 4.833333333333333, "user_numbers": "19", "creator": "Maksym Tymchyk", "last_updated": "2020-08-27 00:00:00"}, {"platform": "chrome", "id": "efmkodhojilpinbapdnoeikgabdclhfg", "key": "cointrack", "name": "Cointrack", "rating": 5.0, "user_numbers": "16", "creator": "Abiodun Adetona", "last_updated": "2017-11-04 00:00:00"}, {"platform": "chrome", "id": "omlcemhghhleeoaoodlipigplhccodbp", "key": "cryptocurrency-price-moni", "name": "Cryptocurrency Price monitoring", "rating": 5.0, "user_numbers": "11", "creator": "Rakesh Narvaneni", "last_updated": "2017-12-31 00:00:00"}, {"platform": "chrome", "id": "giehkbmaeanabblbpagkonkbjdjhnlgl", "key": "citify-instant-exchange", "name": "Citify Instant Exchange", "rating": 0.0, "user_numbers": "11", "creator": "Citify", "last_updated": "2019-09-10 00:00:00"}, {"platform": "chrome", "id": "nobcanbppjbdddoilcpahbkdmjjihnem", "key": "bittrend", "name": "BitTrend", "rating": 0.0, "user_numbers": "11", "creator": "Media3", "last_updated": "2014-09-04 00:00:00"}, {"platform": "chrome", "id": "caknhbobbhcehjebdcpgfodgfbpklblm", "key": "cryptonow", "name": "CryptoNow", "rating": 5.0, "user_numbers": "7", "creator": "jessica.greben1", "last_updated": "2017-05-15 00:00:00"}, {"platform": "chrome", "id": "eeejeggpdpjgkfocdkbepdbkpcpjlncd", "key": "bit-trackers", "name": "Bit Trackers", "rating": 5.0, "user_numbers": "6", "creator": "satyamdev123", "last_updated": "2017-07-13 00:00:00"}, {"platform": "chrome", "id": "glaoldjgoiaajcjcbgpfmnfddioaolop", "key": "cryptocoins-live-rates", "name": "CryptoCoins - Live Rates", "rating": 5.0, "user_numbers": "3", "creator": "ganeshpartheeban", "last_updated": "2019-02-13 00:00:00"}, {"platform": "chrome", "id": "fdhgfeablllkfnbjenoaofhmnnapipdj", "key": "bitcoin-ticker", "name": "Bitcoin Ticker", "rating": 5.0, "user_numbers": "27", "creator": "viktor.derk", "last_updated": "2019-09-16 00:00:00"}, {"platform": "chrome", "id": "gaagaiacppejplcoonchkpgegopmplgl", "key": "b\u7f51\u52a9\u624b-bittrexcom\u7ffb\u8bd1\u52a9\u624b", "name": "B\u7f51\u52a9\u624b bittrex.com\u7ffb\u8bd1\u52a9\u624b", "rating": 5.0, "user_numbers": "834", "creator": "\u6f2b\u6e38\u79d1\u6280", "last_updated": "2017-10-19 00:00:00"}, {"platform": "chrome", "id": "objgonilomonlmlfhgdaedghadgndkpm", "key": "improved-bittrex", "name": "Improved Bittrex", "rating": 4.75, "user_numbers": "118", "creator": "Marvin", "last_updated": "2017-10-25 00:00:00"}, {"platform": "chrome", "id": "enampmoogmjoofjmpobfdmgflljfacnl", "key": "crypto-correct", "name": "Crypto Correct", "rating": 4.35, "user_numbers": "1,000", "creator": "Uzair Farooq", "last_updated": "2017-11-25 00:00:00"}, {"platform": "chrome", "id": "hllgbphaemadbdkhieboiodapooclfan", "key": "ethmarkets-for-bittrex", "name": "EthMarkets For Bittrex", "rating": 0.0, "user_numbers": "10", "creator": "ethmarketextension", "last_updated": "2017-08-19 00:00:00"}, {"platform": "chrome", "id": "cghcagmfbaehgiilpakoioohhnnlbbia", "key": "bittrex-btc-to-usd", "name": "Bittrex BTC to USD", "rating": 0.0, "user_numbers": "5", "creator": "fahad.jameel02", "last_updated": "2018-01-05 00:00:00"}, {"platform": "chrome", "id": "cnogbbmciffpibmkphohpebghmomaemi", "key": "bittube-airtime-donations", "name": "BitTube AirTime, Donations, Adblocker, Wallet", "rating": 4.43448275862069, "user_numbers": "10,000", "creator": "BitTubeINT O\u00dc", "last_updated": "2020-08-21 00:00:00"}, {"platform": "chrome", "id": "gcjmapcnniikogigfhdmemplhbjpgopd", "key": "bittrex-night", "name": "Bittrex night", "rating": 5.0, "user_numbers": "1", "creator": "peter.aupry", "last_updated": "2018-03-14 00:00:00"}, {"platform": "chrome", "id": "mldmimcggjcjklchonpiocpicijmmpph", "key": "bittrexuatu", "name": "Bittrex_uatu", "rating": 0.0, "user_numbers": "1", "creator": "danielostapenko", "last_updated": "2017-11-05 00:00:00"}, {"platform": "chrome", "id": "anipojaclholehpaioakjgkhbdmljmok", "key": "okcash-price-ticker", "name": "OKCash Price Ticker", "rating": 0.0, "user_numbers": "1", "creator": "greenbigfrog", "last_updated": "2017-08-30 00:00:00"}, {"platform": "chrome", "id": "nphlnghlcailopfndihpccmjinilmckb", "key": "cryptocurrency-market-cap", "name": "Cryptocurrency Market Capitalizations", "rating": 5.0, "user_numbers": "67", "creator": "Oaker", "last_updated": "2018-07-11 00:00:00"}, {"platform": "chrome", "id": "nbpfcapniahpdkfmejpogoiamnconiik", "key": "just-bitcoin-cash-sv-tick", "name": "Just Bitcoin Cash Sv Ticker [PRO]", "rating": 0.0, "user_numbers": "1", "creator": "morocco", "last_updated": "2020-11-04 00:00:00"}, {"platform": "chrome", "id": "oleogcnfpjebmamnenggcmmphhghdolj", "key": "cashweb-bb", "name": "CashWeb BB", "rating": 0.0, "user_numbers": "6", "creator": "Kent", "last_updated": "2019-11-28 00:00:00"}]